dictforge/__about__.py
dictforge/__init__.py
dictforge/builder.py
dictforge/config.py
dictforge/export_base.py
dictforge/export_mobi.py
dictforge/export_stardict.py
dictforge/kaikki_utils.py
dictforge/kindle.py
dictforge/kindlegen.py
dictforge/main.py
dictforge/progress_bar.py
dictforge/source_base.py
dictforge/source_freedict.py
dictforge/source_kaikki.py
dictforge/translit.py
dictforge-1.3.0.dist-info/METADATA
dictforge-1.3.0.dist-info/WHEEL
dictforge-1.3.0.dist-info/entry_points.txt
dictforge-1.3.0.dist-info/licenses/LICENSE.txt
dictforge-1.3.0.dist-info/RECORD
