Metadata-Version: 2.4
Name: dictforge
Version: 1.3.0
Summary: Forge Kindle-compatible dictionaries for every language
Project-URL: Homepage, https://andgineer.github.io/dictforge/
Project-URL: Documentation, https://andgineer.github.io/dictforge/
Author-email: Andrey Sorokin <andrey@sorokin.engineer>
License: Copyright (c) 2024 Andrey Sorokin <andrey@sorokin.engineer>
License-File: LICENSE.txt
Keywords: one,two
Classifier: License :: OSI Approved :: MIT License
Classifier: Operating System :: OS Independent
Classifier: Programming Language :: Python :: 3
Requires-Python: >=3.10
Requires-Dist: click>=8.2.0
Requires-Dist: ebook-dictionary-creator
Requires-Dist: requests>=2.31
Requires-Dist: rich-click>=1.8.8
Requires-Dist: tomli; python_version < '3.11'
Requires-Dist: tqdm>=4.66
